gemini_cli_proxy/__init__.py
gemini_cli_proxy/cli.py
gemini_cli_proxy/config.py
gemini_cli_proxy/gemini_client.py
gemini_cli_proxy/models.py
gemini_cli_proxy/openai_adapter.py
gemini_cli_proxy/server.py
gemini_cli_proxy-1.1.0.dist-info/METADATA
gemini_cli_proxy-1.1.0.dist-info/WHEEL
gemini_cli_proxy-1.1.0.dist-info/entry_points.txt
gemini_cli_proxy-1.1.0.dist-info/licenses/LICENSE
gemini_cli_proxy-1.1.0.dist-info/RECORD
