Metadata-Version: 2.4
Name: gemini-cli-proxy
Version: 1.1.0
Summary: OpenAI-compatible API wrapper for Gemini CLI
Author: nettee
License: MIT
License-File: LICENSE
Keywords: api,cli,gemini,openai,proxy
Requires-Python: >=3.8
Requires-Dist: click<9.0,>=8.0.0
Requires-Dist: fastapi<1.0,>=0.104.0
Requires-Dist: pydantic<3.0,>=2.0.0
Requires-Dist: slowapi<1.0,>=0.1.9
Requires-Dist: uvicorn[standard]<1.0,>=0.24.0
